fake_switches/__init__.py
fake_switches/ssh_service.py
fake_switches/switch_configuration.py
fake_switches/switch_core.py
fake_switches/switch_factory.py
fake_switches/telnet_service.py
fake_switches/adapters/__init__.py
fake_switches/adapters/tftp_reader.py
fake_switches/arista/__init__.py
fake_switches/arista/arista_core.py
fake_switches/arista/eapi.py
fake_switches/arista/command_processor/__init__.py
fake_switches/arista/command_processor/config.py
fake_switches/arista/command_processor/config_interface.py
fake_switches/arista/command_processor/config_vlan.py
fake_switches/arista/command_processor/default.py
fake_switches/arista/command_processor/enabled.py
fake_switches/arista/command_processor/terminal_display.py
fake_switches/brocade/__init__.py
fake_switches/brocade/brocade_core.py
fake_switches/brocade/command_processor/__init__.py
fake_switches/brocade/command_processor/config.py
fake_switches/brocade/command_processor/config_interface.py
fake_switches/brocade/command_processor/config_virtual_interface.py
fake_switches/brocade/command_processor/config_virtual_interface_vrrp.py
fake_switches/brocade/command_processor/config_vlan.py
fake_switches/brocade/command_processor/config_vrf.py
fake_switches/brocade/command_processor/default.py
fake_switches/brocade/command_processor/enabled.py
fake_switches/brocade/command_processor/piping.py
fake_switches/cisco/__init__.py
fake_switches/cisco/cisco_core.py
fake_switches/cisco/command_processor/__init__.py
fake_switches/cisco/command_processor/config.py
fake_switches/cisco/command_processor/config_interface.py
fake_switches/cisco/command_processor/config_vlan.py
fake_switches/cisco/command_processor/config_vrf.py
fake_switches/cisco/command_processor/default.py
fake_switches/cisco/command_processor/enabled.py
fake_switches/cisco/command_processor/piping.py
fake_switches/cisco6500/__init__.py
fake_switches/cisco6500/cisco_core.py
fake_switches/cmd/__init__.py
fake_switches/cmd/main.py
fake_switches-1.5.0.dist-info/AUTHORS
fake_switches-1.5.0.dist-info/LICENSE
fake_switches-1.5.0.dist-info/METADATA
fake_switches-1.5.0.dist-info/WHEEL
fake_switches-1.5.0.dist-info/dependency_links.txt
fake_switches-1.5.0.dist-info/entry_points.txt
fake_switches-1.5.0.dist-info/pbr.json
fake_switches-1.5.0.dist-info/top_level.txt
fake_switches-1.5.0.dist-info/RECORD
