Metadata-Version: 2.1
Name: fake-switches
Version: 1.5.0
Summary: A pluggable switch/router command-line simulator
Home-page: https://github.com/internap/fake-switches
Author: Internap Hosting
Author-email: opensource@internap.com
License: Apache Software License
Platform: UNKNOWN
Classifier: Development Status :: 5 - Production/Stable
Classifier: Intended Audience :: Developers
Classifier: Intended Audience :: Information Technology
Classifier: Intended Audience :: System Administrators
Classifier: Intended Audience :: Telecommunications Industry
Classifier: License :: OSI Approved :: Apache Software License
Classifier: Operating System :: POSIX
Classifier: Programming Language :: Python :: 2.7
Classifier: Programming Language :: Python :: 3.5
Classifier: Topic :: Software Development :: Testing
Classifier: Topic :: System :: Emulators
Requires-Dist: tftpy
Requires-Dist: netaddr (>=0.7.13)
Requires-Dist: Twisted[conch] (<17.0,>=16.6.0)
Requires-Dist: lxml (>=3.7)
Requires-Dist: cryptography (<3) ; (python_version<'3')
Requires-Dist: cryptography (<3) ; (python_version=='3.5')
